sqlite_connector/__init__.py
sqlite_connector/sqlite.py
sqlite_connector-0.1.0.dist-info/LICENSE
sqlite_connector-0.1.0.dist-info/METADATA
sqlite_connector-0.1.0.dist-info/WHEEL
sqlite_connector-0.1.0.dist-info/top_level.txt
sqlite_connector-0.1.0.dist-info/RECORD
