Metadata-Version: 2.1
Name: sqlite-connector
Version: 0.1.0
Summary: Python package with SQLite convenience functions
Home-page: https://github.com/fylein/sqlite-connector
Author: Shwetabh Kumar
Author-email: shwetabh.kumar@fyle.in
License: MIT
Keywords: fyle,db,python,sdk,sqlite
Platform: UNKNOWN
Classifier: Topic :: Internet :: WWW/HTTP
Classifier: Intended Audience :: Developers
Classifier: Programming Language :: Python :: 3
Classifier: License :: OSI Approved :: MIT License
Classifier: Operating System :: OS Independent
Requires-Dist: logger (==1.4)
